{
  "default:normal": {
    "child_offset_y": -2,
    "components": [
      {
        "type": "border_image",
        "boarderH":8,
        "boarderV": 8,
        "loc": "cubecraft:/gui/control/topbar.png",
        "pos": [0,1,0,1]
      },
      {
        "type": "font",
        "binding": "topbar:back",
        "size": 8,
        "color": 0,
        "line_offset": -3,
        "pos": [0,0.4]
      }
    ]
  },
  "default:back_pressed":{
    "child_offset_y": -2,
    "components": [
      {
        "type": "border_image",
        "boarderH":8,
        "boarderV": 8,
        "loc": "cubecraft:/gui/control/topbar.png",
        "pos": [0,1,0,1]
      },
      {
        "type": "font",
        "binding": "topbar:back",
        "size": 8,
        "color": 0,
        "line_offset": -4,
        "pos": [0,0.3]
      }
    ]
  }
}